dataquery/__init__.py
dataquery/dataquery.py
dataquery/core/__init__.py
dataquery/core/column.py
dataquery/core/database.py
dataquery/core/delete.py
dataquery/core/insert.py
dataquery/core/retrieval.py
dataquery/core/table.py
dataquery/core/update.py
dataquery/utils/__init__.py
dataquery/utils/data_utils.py
dataquery/utils/db_utils.py
dataquery/utils/logging_utils.py
dataquery-0.1.1.dist-info/LICENSE
dataquery-0.1.1.dist-info/METADATA
dataquery-0.1.1.dist-info/WHEEL
dataquery-0.1.1.dist-info/top_level.txt
dataquery-0.1.1.dist-info/RECORD
